zita/__init__.py
zita/app.py
zita/bin/__init__.py
zita/bin/zita
zita/celery.py
zita/data/__init__.py
zita/data/dedup.py
zita/data/photo.py
zita/rpc.py
zita/serve/__init__.py
zita/serve/evaluate.py
zita/serve/predict.py
zita/serve/redis.py
zita/serve/resolver.py
zita/serve/schema.py
zita/serve/typedef.gql
zita/settings.py
zita/tasks.py
zita/train/__init__.py
zita/train/basic.py
zita/utils/__init__.py
zita/utils/parallel_runner.py
zita-0.0.1.dev0.dist-info/WHEEL
zita-0.0.1.dev0.dist-info/METADATA
zita-0.0.1.dev0.dist-info/RECORD
