Metadata-Version: 2.1
Name: zita
Version: 0.0.1.dev0
Summary: Zillion Image Tagging App
Home-page: https://github.com/ktmud/zita
License: Apache-2.0
Author: Jesse Yang
Author-email: hello@yjc.me
Requires-Python: >=3.7
Classifier: License :: OSI Approved :: Apache Software License
Classifier: Programming Language :: Python :: 3
Classifier: Programming Language :: Python :: 3.7
Requires-Dist: ariadne (>=0.6.0)
Requires-Dist: celery[redis] (>=4.3.0,<5.0.0)
Requires-Dist: fastai (>=1.0.57)
Requires-Dist: imagehash (>=4.0)
Requires-Dist: orjson (>=2.0.7,<3.0.0)
Requires-Dist: pyzmq (>=18.1.0,<19.0.0)
Requires-Dist: redis (>=3.3.8,<4.0.0)
Requires-Dist: uvicorn (>=0.8.6)
Project-URL: Repository, https://github.com/ktmud/zita
